PdbTextMateSupport.py
pdbtmsupport
setup.cfg
setup.py
PdbTextMateSupport2.egg-info/PKG-INFO
PdbTextMateSupport2.egg-info/SOURCES.txt
PdbTextMateSupport2.egg-info/dependency_links.txt
PdbTextMateSupport2.egg-info/top_level.txt