Metadata-Version: 1.0
Name: PdbTextMateSupport2
Version: 0.5
Summary: Display source code in TextMate while debugging with pdb.
Home-page: https://github.com/schinckel/pdbtextmatesupport
Author: Matthew Schinckel
Author-email: matt@schinckel.net
License: GPL
Download-URL: http://cheeseshop.python.org/pypi/PdbTextMateSupport2/
Keywords: textmate pdb
Platform: Mac OS X
Classifier: Development Status :: 4 - Beta
Classifier: Environment :: Console
Classifier: Environment :: MacOS X
Classifier: Intended Audience :: Developers
Classifier: Intended Audience :: System Administrators
Classifier: License :: OSI Approved :: GNU General Public License (GPL)
Classifier: Operating System :: MacOS :: MacOS X
Classifier: Programming Language :: Python
Classifier: Topic :: Software Development :: Debuggers
Classifier: Topic :: Text Editors
